flask_service_factory/__init__.py
flask_service_factory/app_factory.py
flask_service_factory/service_factory.py
flask_service_factory-0.1.0.dist-info/METADATA
flask_service_factory-0.1.0.dist-info/RECORD
flask_service_factory-0.1.0.dist-info/WHEEL
flask_service_factory-0.1.0.dist-info/top_level.txt
